LICENSE
MANIFEST.in
README.md
setup.cfg
setup.py
django_hhypermap.egg-info/PKG-INFO
django_hhypermap.egg-info/SOURCES.txt
django_hhypermap.egg-info/dependency_links.txt
django_hhypermap.egg-info/not-zip-safe
django_hhypermap.egg-info/requires.txt
django_hhypermap.egg-info/top_level.txt
hypermap/__init__.py
hypermap/celeryapp.py
hypermap/context_processors.py
hypermap/urls.py
hypermap/wsgi.py
hypermap/aggregator/__init__.py
hypermap/aggregator/admin.py
hypermap/aggregator/elasticsearch_client.py
hypermap/aggregator/enums.py
hypermap/aggregator/models.py
hypermap/aggregator/populate_database.py
hypermap/aggregator/solr.py
hypermap/aggregator/tasks.py
hypermap/aggregator/urls.py
hypermap/aggregator/utils.py
hypermap/aggregator/views.py
hypermap/aggregator/management/__init__.py
hypermap/aggregator/management/commands/__init__.py
hypermap/aggregator/management/commands/check_services.py
hypermap/aggregator/management/commands/import_services.py
hypermap/aggregator/tests/__init__.py
hypermap/aggregator/tests/test_metadata.py
hypermap/aggregator/tests/test_page_render.py
hypermap/aggregator/tests/test_warper.py
hypermap/aggregator/tests/test_wms.py
hypermap/aggregator/tests/test_worldmap.py
hypermap/aggregator/tests/mocks/__init__.py
hypermap/aggregator/tests/mocks/warper.py
hypermap/aggregator/tests/mocks/wms.py
hypermap/aggregator/tests/mocks/worldmap.py
hypermap/dynasty/__init__.py
hypermap/dynasty/admin.py
hypermap/dynasty/models.py
hypermap/dynasty/tests.py
hypermap/dynasty/utils.py
hypermap/dynasty/views.py
hypermap/proxymap/__init__.py
hypermap/proxymap/models.py
hypermap/proxymap/tests.py
hypermap/proxymap/urls.py
hypermap/proxymap/views.py
hypermap/search/__init__.py
hypermap/search/admin.py
hypermap/search/models.py
hypermap/search/pycsw_local_mappings.py
hypermap/search/tests.py
hypermap/search/urls.py
hypermap/search/views.py
hypermap/settings/__init__.py
hypermap/settings/_ubuntu.py
hypermap/settings/_vagrant.py
hypermap/settings/default.py
hypermap/settings/test.py
hypermap/static/bootstrap/css/bootstrap-theme.css
hypermap/static/bootstrap/css/bootstrap-theme.min.css
hypermap/static/bootstrap/css/bootstrap.css
hypermap/static/bootstrap/css/bootstrap.min.css
