Metadata-Version: 1.1
Name: django-hhypermap
Version: 0.2
Summary: Use Registry in your django projects.
Home-page: https://github.com/cga-harvard/HHypermap
Author: UNKNOWN
Author-email: UNKNOWN
License: See LICENSE file.
Download-URL: https://github.com/cga-harvard/HHypermap
Platform: UNKNOWN
Classifier: Development Status :: 1 - Planning
